[{"date": "1/22/20", "confirm": 0, "recover": 0, "deaths": 0, "confirm_daily": 0, "recover_daily": 0, "deaths_daily": 0}, {"date": "1/23/20", "confirm": 0, "recover": 0, "deaths": 0, "confirm_daily": 0, "recover_daily": 0, "deaths_daily": 0}, {"date": "1/24/20", "confirm": 0, "recover": 0, "deaths": 0, "confirm_daily": 0, "recover_daily": 0, "deaths_daily": 0}, {"date": "1/25/20", "confirm": 0, "recover": 0, "deaths": 0, "confirm_daily": 0, "recover_daily": 0, "deaths_daily": 0}, {"date": "1/26/20", "confirm": 0, "recover": 0, "deaths": 0, "confirm_daily": 0, "recover_daily": 0, "deaths_daily": 0}, {"date": "1/27/20", "confirm": 0, "recover": 0, "deaths": 0, "confirm_daily": 0, "recover_daily": 0, "deaths_daily": 0}, {"date": "1/28/20", "confirm": 0, "recover": 0, "deaths": 0, "confirm_daily": 0, "recover_daily": 0, "deaths_daily": 0}, {"date": "1/29/20", "confirm": 0, "recover": 0, "deaths": 0, "confirm_daily": 0, "recover_daily": 0, "deaths_daily": 0}, {"date": "1/30/20", "confirm": 0, "recover": 0, "deaths": 0, "confirm_daily": 0, "recover_daily": 0, "deaths_daily": 0}, {"date": "1/31/20", "confirm": 0, "recover": 0, "deaths": 0, "confirm_daily": 0, "recover_daily": 0, "deaths_daily": 0}, {"date": "2/1/20", "confirm": 0, "recover": 0, "deaths": 0, "confirm_daily": 0, "recover_daily": 0, "deaths_daily": 0}, {"date": "2/2/20", "confirm": 0, "recover": 0, "deaths": 0, "confirm_daily": 0, "recover_daily": 0, "deaths_daily": 0}, {"date": "2/3/20", "confirm": 0, "recover": 0, "deaths": 0, "confirm_daily": 0, "recover_daily": 0, "deaths_daily": 0}, {"date": "2/4/20", "confirm": 0, "recover": 0, "deaths": 0, "confirm_daily": 0, "recover_daily": 0, "deaths_daily": 0}, {"date": "2/5/20", "confirm": 0, "recover": 0, "deaths": 0, "confirm_daily": 0, "recover_daily": 0, "deaths_daily": 0}, {"date": "2/6/20", "confirm": 0, "recover": 0, "deaths": 0, "confirm_daily": 0, "recover_daily": 0, "deaths_daily": 0}, {"date": "2/7/20", "confirm": 0, "recover": 0, "deaths": 0, "confirm_daily": 0, "recover_daily": 0, "deaths_daily": 0}, {"date": "2/8/20", "confirm": 0, "recover": 0, "deaths": 0, "confirm_daily": 0, "recover_daily": 0, "deaths_daily": 0}, {"date": "2/9/20", "confirm": 0, "recover": 0, "deaths": 0, "confirm_daily": 0, "recover_daily": 0, "deaths_daily": 0}, {"date": "2/10/20", "confirm": 0, "recover": 0, "deaths": 0, "confirm_daily": 0, "recover_daily": 0, "deaths_daily": 0}, {"date": "2/11/20", "confirm": 0, "recover": 0, "deaths": 0, "confirm_daily": 0, "recover_daily": 0, "deaths_daily": 0}, {"date": "2/12/20", "confirm": 0, "recover": 0, "deaths": 0, "confirm_daily": 0, "recover_daily": 0, "deaths_daily": 0}, {"date": "2/13/20", "confirm": 0, "recover": 0, "deaths": 0, "confirm_daily": 0, "recover_daily": 0, "deaths_daily": 0}, {"date": "2/14/20", "confirm": 0, "recover": 0, "deaths": 0, "confirm_daily": 0, "recover_daily": 0, "deaths_daily": 0}, {"date": "2/15/20", "confirm": 0, "recover": 0, "deaths": 0, "confirm_daily": 0, "recover_daily": 0, "deaths_daily": 0}, {"date": "2/16/20", "confirm": 0, "recover": 0, "deaths": 0, "confirm_daily": 0, "recover_daily": 0, "deaths_daily": 0}, {"date": "2/17/20", "confirm": 0, "recover": 0, "deaths": 0, "confirm_daily": 0, "recover_daily": 0, "deaths_daily": 0}, {"date": "2/18/20", "confirm": 0, "recover": 0, "deaths": 0, "confirm_daily": 0, "recover_daily": 0, "deaths_daily": 0}, {"date": "2/19/20", "confirm": 0, "recover": 0, "deaths": 0, "confirm_daily": 0, "recover_daily": 0, "deaths_daily": 0}, {"date": "2/20/20", "confirm": 0, "recover": 0, "deaths": 0, "confirm_daily": 0, "recover_daily": 0, "deaths_daily": 0}, {"date": "2/21/20", "confirm": 0, "recover": 0, "deaths": 0, "confirm_daily": 0, "recover_daily": 0, "deaths_daily": 0}, {"date": "2/22/20", "confirm": 0, "recover": 0, "deaths": 0, "confirm_daily": 0, "recover_daily": 0, "deaths_daily": 0}, {"date": "2/23/20", "confirm": 0, "recover": 0, "deaths": 0, "confirm_daily": 0, "recover_daily": 0, "deaths_daily": 0}, {"date": "2/24/20", "confirm": 0, "recover": 0, "deaths": 0, "confirm_daily": 0, "recover_daily": 0, "deaths_daily": 0}, {"date": "2/25/20", "confirm": 0, "recover": 0, "deaths": 0, "confirm_daily": 0, "recover_daily": 0, "deaths_daily": 0}, {"date": "2/26/20", "confirm": 1, "recover": 0, "deaths": 0, "confirm_daily": 1, "recover_daily": 0, "deaths_daily": 0}, {"date": "2/27/20", "confirm": 1, "recover": 0, "deaths": 0, "confirm_daily": 0, "recover_daily": 0, "deaths_daily": 0}, {"date": "2/28/20", "confirm": 3, "recover": 0, "deaths": 0, "confirm_daily": 2, "recover_daily": 0, "deaths_daily": 0}, {"date": "2/29/20", "confirm": 3, "recover": 0, "deaths": 0, "confirm_daily": 0, "recover_daily": 0, "deaths_daily": 0}, {"date": "3/1/20", "confirm": 3, "recover": 0, "deaths": 0, "confirm_daily": 0, "recover_daily": 0, "deaths_daily": 0}, {"date": "3/2/20", "confirm": 3, "recover": 0, "deaths": 0, "confirm_daily": 0, "recover_daily": 0, "deaths_daily": 0}, {"date": "3/3/20", "confirm": 3, "recover": 0, "deaths": 0, "confirm_daily": 0, "recover_daily": 0, "deaths_daily": 0}, {"date": "3/4/20", "confirm": 4, "recover": 1, "deaths": 0, "confirm_daily": 1, "recover_daily": 1, "deaths_daily": 0}, {"date": "3/5/20", "confirm": 6, "recover": 1, "deaths": 0, "confirm_daily": 2, "recover_daily": 0, "deaths_daily": 0}, {"date": "3/6/20", "confirm": 9, "recover": 1, "deaths": 0, "confirm_daily": 3, "recover_daily": 0, "deaths_daily": 0}, {"date": "3/7/20", "confirm": 9, "recover": 3, "deaths": 0, "confirm_daily": 0, "recover_daily": 2, "deaths_daily": 0}, {"date": "3/8/20", "confirm": 15, "recover": 3, "deaths": 0, "confirm_daily": 6, "recover_daily": 0, "deaths_daily": 0}, {"date": "3/9/20", "confirm": 15, "recover": 3, "deaths": 0, "confirm_daily": 0, "recover_daily": 0, "deaths_daily": 0}, {"date": "3/10/20", "confirm": 25, "recover": 3, "deaths": 0, "confirm_daily": 10, "recover_daily": 0, "deaths_daily": 0}, {"date": "3/11/20", "confirm": 45, "recover": 6, "deaths": 0, "confirm_daily": 20, "recover_daily": 3, "deaths_daily": 0}, {"date": "3/12/20", "confirm": 49, "recover": 6, "deaths": 0, "confirm_daily": 4, "recover_daily": 0, "deaths_daily": 0}, {"date": "3/13/20", "confirm": 89, "recover": 7, "deaths": 0, "confirm_daily": 40, "recover_daily": 1, "deaths_daily": 0}, {"date": "3/14/20", "confirm": 123, "recover": 9, "deaths": 0, "confirm_daily": 34, "recover_daily": 2, "deaths_daily": 0}, {"date": "3/15/20", "confirm": 131, "recover": 9, "deaths": 0, "confirm_daily": 8, "recover_daily": 0, "deaths_daily": 0}, {"date": "3/16/20", "confirm": 158, "recover": 9, "deaths": 0, "confirm_daily": 27, "recover_daily": 0, "deaths_daily": 0}, {"date": "3/17/20", "confirm": 184, "recover": 16, "deaths": 0, "confirm_daily": 26, "recover_daily": 7, "deaths_daily": 0}, {"date": "3/18/20", "confirm": 260, "recover": 19, "deaths": 0, "confirm_daily": 76, "recover_daily": 3, "deaths_daily": 0}, {"date": "3/19/20", "confirm": 277, "recover": 25, "deaths": 0, "confirm_daily": 17, "recover_daily": 6, "deaths_daily": 0}, {"date": "3/20/20", "confirm": 308, "recover": 25, "deaths": 0, "confirm_daily": 31, "recover_daily": 0, "deaths_daily": 0}, {"date": "3/21/20", "confirm": 367, "recover": 52, "deaths": 0, "confirm_daily": 59, "recover_daily": 27, "deaths_daily": 0}, {"date": "3/22/20", "confirm": 433, "recover": 64, "deaths": 3, "confirm_daily": 66, "recover_daily": 12, "deaths_daily": 3}, {"date": "3/23/20", "confirm": 576, "recover": 64, "deaths": 7, "confirm_daily": 143, "recover_daily": 0, "deaths_daily": 4}, {"date": "3/24/20", "confirm": 794, "recover": 79, "deaths": 11, "confirm_daily": 218, "recover_daily": 15, "deaths_daily": 4}, {"date": "3/25/20", "confirm": 906, "recover": 86, "deaths": 17, "confirm_daily": 112, "recover_daily": 7, "deaths_daily": 6}, {"date": "3/26/20", "confirm": 1029, "recover": 94, "deaths": 23, "confirm_daily": 123, "recover_daily": 8, "deaths_daily": 6}, {"date": "3/27/20", "confirm": 1292, "recover": 115, "deaths": 26, "confirm_daily": 263, "recover_daily": 21, "deaths_daily": 3}, {"date": "3/28/20", "confirm": 1452, "recover": 139, "deaths": 37, "confirm_daily": 160, "recover_daily": 24, "deaths_daily": 11}, {"date": "3/29/20", "confirm": 1815, "recover": 206, "deaths": 43, "confirm_daily": 363, "recover_daily": 67, "deaths_daily": 6}, {"date": "3/30/20", "confirm": 2109, "recover": 209, "deaths": 65, "confirm_daily": 294, "recover_daily": 3, "deaths_daily": 22}, {"date": "3/31/20", "confirm": 2245, "recover": 220, "deaths": 82, "confirm_daily": 136, "recover_daily": 11, "deaths_daily": 17}, {"date": "4/1/20", "confirm": 2460, "recover": 252, "deaths": 92, "confirm_daily": 215, "recover_daily": 32, "deaths_daily": 10}, {"date": "4/2/20", "confirm": 2738, "recover": 267, "deaths": 115, "confirm_daily": 278, "recover_daily": 15, "deaths_daily": 23}, {"date": "4/3/20", "confirm": 3183, "recover": 283, "deaths": 133, "confirm_daily": 445, "recover_daily": 16, "deaths_daily": 18}, {"date": "4/4/20", "confirm": 3613, "recover": 329, "deaths": 146, "confirm_daily": 430, "recover_daily": 46, "deaths_daily": 13}, {"date": "4/5/20", "confirm": 3864, "recover": 374, "deaths": 151, "confirm_daily": 251, "recover_daily": 45, "deaths_daily": 5}, {"date": "4/6/20", "confirm": 4057, "recover": 406, "deaths": 176, "confirm_daily": 193, "recover_daily": 32, "deaths_daily": 25}, {"date": "4/7/20", "confirm": 4417, "recover": 460, "deaths": 197, "confirm_daily": 360, "recover_daily": 54, "deaths_daily": 21}, {"date": "4/8/20", "confirm": 4761, "recover": 528, "deaths": 220, "confirm_daily": 344, "recover_daily": 68, "deaths_daily": 23}, {"date": "4/9/20", "confirm": 5202, "recover": 647, "deaths": 248, "confirm_daily": 441, "recover_daily": 119, "deaths_daily": 28}, {"date": "4/10/20", "confirm": 5467, "recover": 729, "deaths": 270, "confirm_daily": 265, "recover_daily": 82, "deaths_daily": 22}, {"date": "4/11/20", "confirm": 5990, "recover": 758, "deaths": 291, "confirm_daily": 523, "recover_daily": 29, "deaths_daily": 21}, {"date": "4/12/20", "confirm": 6300, "recover": 852, "deaths": 316, "confirm_daily": 310, "recover_daily": 94, "deaths_daily": 25}, {"date": "4/13/20", "confirm": 6633, "recover": 914, "deaths": 331, "confirm_daily": 333, "recover_daily": 62, "deaths_daily": 15}, {"date": "4/14/20", "confirm": 6879, "recover": 1051, "deaths": 351, "confirm_daily": 246, "recover_daily": 137, "deaths_daily": 20}, {"date": "4/15/20", "confirm": 7216, "recover": 1217, "deaths": 372, "confirm_daily": 337, "recover_daily": 166, "deaths_daily": 21}, {"date": "4/16/20", "confirm": 7707, "recover": 1357, "deaths": 392, "confirm_daily": 491, "recover_daily": 140, "deaths_daily": 20}, {"date": "4/17/20", "confirm": 8067, "recover": 1508, "deaths": 411, "confirm_daily": 360, "recover_daily": 151, "deaths_daily": 19}, {"date": "4/18/20", "confirm": 8418, "recover": 1730, "deaths": 421, "confirm_daily": 351, "recover_daily": 222, "deaths_daily": 10}, {"date": "4/19/20", "confirm": 8746, "recover": 1892, "deaths": 451, "confirm_daily": 328, "recover_daily": 162, "deaths_daily": 30}, {"date": "4/20/20", "confirm": 8936, "recover": 2017, "deaths": 478, "confirm_daily": 190, "recover_daily": 125, "deaths_daily": 27}, {"date": "4/21/20", "confirm": 9242, "recover": 2153, "deaths": 498, "confirm_daily": 306, "recover_daily": 136, "deaths_daily": 20}, {"date": "4/22/20", "confirm": 9710, "recover": 2406, "deaths": 524, "confirm_daily": 468, "recover_daily": 253, "deaths_daily": 26}, {"date": "4/23/20", "confirm": 10096, "recover": 2478, "deaths": 545, "confirm_daily": 386, "recover_daily": 72, "deaths_daily": 21}, {"date": "4/24/20", "confirm": 10417, "recover": 2817, "deaths": 567, "confirm_daily": 321, "recover_daily": 339, "deaths_daily": 22}, {"date": "4/25/20", "confirm": 10635, "recover": 2890, "deaths": 601, "confirm_daily": 218, "recover_daily": 73, "deaths_daily": 34}, {"date": "4/26/20", "confirm": 11036, "recover": 3054, "deaths": 619, "confirm_daily": 401, "recover_daily": 164, "deaths_daily": 18}, {"date": "4/27/20", "confirm": 11339, "recover": 3141, "deaths": 641, "confirm_daily": 303, "recover_daily": 87, "deaths_daily": 22}, {"date": "4/28/20", "confirm": 11616, "recover": 3404, "deaths": 663, "confirm_daily": 277, "recover_daily": 263, "deaths_daily": 22}, {"date": "4/29/20", "confirm": 11978, "recover": 3569, "deaths": 693, "confirm_daily": 362, "recover_daily": 165, "deaths_daily": 30}, {"date": "4/30/20", "confirm": 12240, "recover": 4017, "deaths": 717, "confirm_daily": 262, "recover_daily": 448, "deaths_daily": 24}, {"date": "5/1/20", "confirm": 12567, "recover": 4328, "deaths": 744, "confirm_daily": 327, "recover_daily": 311, "deaths_daily": 27}, {"date": "5/2/20", "confirm": 12732, "recover": 4547, "deaths": 771, "confirm_daily": 165, "recover_daily": 219, "deaths_daily": 27}, {"date": "5/3/20", "confirm": 13163, "recover": 4869, "deaths": 790, "confirm_daily": 431, "recover_daily": 322, "deaths_daily": 19}, {"date": "5/4/20", "confirm": 13512, "recover": 5269, "deaths": 818, "confirm_daily": 349, "recover_daily": 400, "deaths_daily": 28}, {"date": "5/5/20", "confirm": 13837, "recover": 5454, "deaths": 841, "confirm_daily": 325, "recover_daily": 185, "deaths_daily": 23}, {"date": "5/6/20", "confirm": 14107, "recover": 5788, "deaths": 864, "confirm_daily": 270, "recover_daily": 334, "deaths_daily": 23}, {"date": "5/7/20", "confirm": 14499, "recover": 6144, "deaths": 888, "confirm_daily": 392, "recover_daily": 356, "deaths_daily": 24}, {"date": "5/8/20", "confirm": 14811, "recover": 6423, "deaths": 923, "confirm_daily": 312, "recover_daily": 279, "deaths_daily": 35}, {"date": "5/9/20", "confirm": 15131, "recover": 6912, "deaths": 939, "confirm_daily": 320, "recover_daily": 489, "deaths_daily": 16}, {"date": "5/10/20", "confirm": 15362, "recover": 7051, "deaths": 961, "confirm_daily": 231, "recover_daily": 139, "deaths_daily": 22}, {"date": "5/11/20", "confirm": 15588, "recover": 7245, "deaths": 982, "confirm_daily": 226, "recover_daily": 194, "deaths_daily": 21}, {"date": "5/12/20", "confirm": 15778, "recover": 7685, "deaths": 1002, "confirm_daily": 190, "recover_daily": 440, "deaths_daily": 20}, {"date": "5/13/20", "confirm": 16002, "recover": 7961, "deaths": 1036, "confirm_daily": 224, "recover_daily": 276, "deaths_daily": 34}]